find2deny/__init__.py
find2deny/__version__.py
find2deny/cli.py
find2deny/config_parser.py
find2deny/db_connection.py
find2deny/execution.py
find2deny/judgment.py
find2deny/log-data.sql
find2deny/log_parser.py
find2deny-0.2.10.data/data/find2deny/rules.toml
find2deny-0.2.10.dist-info/METADATA
find2deny-0.2.10.dist-info/WHEEL
find2deny-0.2.10.dist-info/entry_points.txt
find2deny-0.2.10.dist-info/top_level.txt
find2deny-0.2.10.dist-info/RECORD
