Metadata-Version: 2.1
Name: find2deny
Version: 0.2.10
Summary: find Bot IPs in log file to firewall them
Home-page: http://mathcoach.htwsaar.de/
Author: Hong-Phuc Bui <hong-phuc (dot) bui (at) htwsaar (dot) de>
Author-email: UNKNOWN
License: MIT
Keywords: logfile-analyse
Platform: UNKNOWN
Classifier: Development Status :: 3 - Alpha
Classifier: License :: OSI Approved :: MIT License
Classifier: Programming Language :: Python :: 3.6
Classifier: Programming Language :: Python :: 3.7
Classifier: Topic :: Internet :: Log Analysis
Requires-Dist: importlib-resources
Requires-Dist: ipaddress
Requires-Dist: ipwhois
Requires-Dist: pendulum
Requires-Dist: python-magic
Requires-Dist: toml
